pytest_playwright_visual/__init__.py
pytest_playwright_visual/plugin.py
pytest_playwright_visual-2.1.2.dist-info/METADATA
pytest_playwright_visual-2.1.2.dist-info/WHEEL
pytest_playwright_visual-2.1.2.dist-info/entry_points.txt
pytest_playwright_visual-2.1.2.dist-info/top_level.txt
pytest_playwright_visual-2.1.2.dist-info/RECORD
