Metadata-Version: 2.1
Name: pytest-playwright-visual
Version: 2.1.2
Summary: A pytest fixture for visual testing with Playwright
Home-page: https://github.com/symon-storozhenko/pytest-playwright-visual
Author: Symon Storozhenko
Author-email: symon.storozhenko@gmail.com
License: UNKNOWN
Platform: UNKNOWN
Classifier: Programming Language :: Python :: 3
Classifier: Programming Language :: Python :: 3.8
Classifier: Programming Language :: Python :: 3.9
Classifier: Programming Language :: Python :: 3.10
Classifier: License :: OSI Approved :: Apache Software License
Classifier: Operating System :: OS Independent
Classifier: Framework :: Pytest
Requires-Python: >=3.8
Requires-Dist: pytest-playwright (>=0.1.2)
Requires-Dist: Pillow (>=8.2.0)
Requires-Dist: pixelmatch (>=0.3.0)
